Metadata-Version: 1.1
Name: gwpca
Version: 0.1.1
Summary: An example girder worker extension
Home-page: UNKNOWN
Author: Chris Kotfila
Author-email: chris.kotfila@kitware.com
License: Apache v2
Platform: UNKNOWN
Classifier: Development Status :: 2 - Pre-Alpha
Classifier: License :: OSI Approved :: Apache Software License
Classifier: Topic :: Scientific/Engineering
Classifier: Intended Audience :: Science/Research
Classifier: Natural Language :: English
Classifier: Programming Language :: Python
